{
	"animations": [
		{
			"loop": false,
			"offsets": [
				-143,
				54
			],
			"anim": "singUP",
			"fps": 24,
			"name": "up",
			"indices": []
		},
		{
			"loop": false,
			"offsets": [
				-35,
				-99
			],
			"anim": "singDOWN",
			"fps": 24,
			"name": "down",
			"indices": []
		},
		{
			"loop": false,
			"offsets": [
				0,
				-1
			],
			"anim": "singLEFT",
			"fps": 24,
			"name": "left",
			"indices": []
		},
		{
			"loop": false,
			"offsets": [
				-10,
				2
			],
			"anim": "singRIGHT",
			"fps": 24,
			"name": "right",
			"indices": []
		},
		{
			"offsets": [
				-4,
				-3
			],
			"loop": false,
			"fps": 24,
			"anim": "idle",
			"indices": [],
			"name": "idle"
		}
	],
	"vocals_file": "gf",
	"no_antialiasing": false,
	"image": "characters/burgg/burgerboobookeys",
	"position": [
		0,
		270
	],
	"healthicon": "kanekeys",
	"flip_x": false,
	"healthbar_colors": [
		34,
		177,
		76
	],
	"camera_position": [
		-70,
		20
	],
	"sing_duration": 5.9,
	"scale": 1,
	"_editor_isPlayer": false
}